printer.v
// Date: 2025.2.27
// Author: LiPtP
// Description: 8-bit Printer with 8 cycles of printing delay and 4 clock cycles of 
module PRINTER (
    i_tr,
    i_pd,
    o_rdy,
    i_clk,
    i_rst_n,
    o_data
);
  // interfaces
  input wire i_clk;
  input wire i_rst_n;
  input wire i_tr;
  input wire [7:0] i_pd;
  output wire o_rdy;
  output wire [7:0] o_data;

  // inside printer
  reg [7:0] delay_buffer[0:3];  // for delaying 4 cycles
  reg [2:0] count;
  reg state, next_state;

  parameter IDLE = 1'b0;
  parameter BUSY = 1'b1;


  always @(posedge i_clk or negedge i_rst_n) begin
    if (!i_rst_n) begin
      state <= IDLE;
    end else begin
      state <= next_state;
    end
  end

  // state transition
  always @(*) begin
    case (state)
      IDLE: begin
        if (i_tr) begin
          next_state <= BUSY;
        end else begin
          next_state <= IDLE;
        end
      end
      BUSY: begin
        // we will wait 8 clock cycles for printer to print, even though the printing process only needs 4.
        if (count == 3'b111) begin
          next_state <= IDLE;
        end else begin
          next_state <= BUSY;
        end
      end
      default: begin
        next_state <= IDLE;
      end
    endcase

  end

  // counter
  always @(posedge i_clk or negedge i_rst_n) begin
    if (!i_rst_n) begin
      count <= 3'b0;
    end else begin
      case (state)
        IDLE: begin
          count <= 3'b0;
        end
        BUSY: begin
          count <= count + 1;
        end
        default: begin
          count <= 3'b0;
        end
      endcase
    end
  end

  // delay four cycles to simulate printing process
  always @(posedge i_clk) begin
    if (state == BUSY) begin
      delay_buffer[0] <= i_pd;
    end
  end

  always @(posedge i_clk) begin
    if (state == BUSY) begin
      delay_buffer[1] <= delay_buffer[0];
    end
  end

  always @(posedge i_clk) begin
    if (state == BUSY) begin
      delay_buffer[2] <= delay_buffer[1];
    end
  end

  always @(posedge i_clk) begin
    if (state == BUSY) begin
      delay_buffer[3] <= delay_buffer[2];
    end
  end

  assign o_data = delay_buffer[3];
  assign o_rdy  = (state == IDLE) ? 1'b1 : 1'b0;

endmodule

poc.v
// Date: 2025.3.20
// Author: LiPtP
// Description: 8-bit Parallel Output Controller

module POC (
    i_addr,
    o_dout,
    i_din,
    i_rw,
    i_clk,
    i_rst_n,
    i_mode,
    o_irq,
    i_rdy,
    o_tr,
    o_pd
);

  // From Top module

  input wire i_mode;  // 0 = query, 1 = interrupt

  // From/to Processor

  input wire i_addr;  // 0: status, 1: buffer    
  input wire i_clk;
  input wire i_rst_n;
  input wire i_rw;  // 0: read, 1: write
  input wire [7:0] i_din;  // status/data from Processor
  output wire [7:0] o_dout;  // status to CPU
  output wire o_irq;  // 0: interrupt

  // From/to Printer
  input wire i_rdy;
  output wire o_tr;
  output [7:0] o_pd;

  // Inside POC
  reg mode;
  reg [7:0] status;
  reg [7:0] buffer;
  reg [7:0] printer_data;
  reg enable_printer;
  wire interrupt;
  reg ready;
  reg tr_triggered;


  // State Params

  parameter IDLE = 3'b0;
  // Wait for CPU response
  parameter POLLING_CPU_WRITE = 3'b001;
  // POC will receive data from processor using polling method
  parameter POLLING_TO_PRINTER = 3'b010;
  // POC will transmit data to printer
  parameter INTERRUPT_CPU_WRITE = 3'b011;
  // POC will receive data from processor using interrupt method
  parameter INTERRUPT_TO_PRINTER = 3'b100;
  // POC will transmit data to printer


  reg [2:0] state, next_state;


  // initial 
  always @(posedge i_clk or negedge i_rst_n) begin
    if (!i_rst_n) begin
      state <= IDLE;
      ready <= 'b0;  // maybe there is a more beautiful solution
      mode  <= 'b0;
    end else begin
      state <= next_state;
      ready <= i_rdy;
      mode  <= i_mode;
    end
  end

  // state transition
  always @(*) begin
    case (state)
      IDLE: begin
        if (i_rw == 1'b1) begin
          if (status[0] == 0) begin  // query
            next_state = POLLING_CPU_WRITE;
          end else begin
            if (interrupt == 1'b1) begin
              next_state = INTERRUPT_CPU_WRITE;
            end
          end
        end else begin
          next_state = IDLE;
        end
      end
      POLLING_CPU_WRITE: begin
        if (status[7] == 0) begin
          next_state = POLLING_TO_PRINTER;
        end else begin
          next_state = POLLING_CPU_WRITE;
        end
      end
      POLLING_TO_PRINTER: begin
        if (i_rdy == 'b1 && ready == 'b0) begin
          next_state = IDLE;
        end else begin
          next_state = POLLING_TO_PRINTER;
        end
      end
      INTERRUPT_CPU_WRITE: begin
        if (status[7] == 0) begin
          next_state = INTERRUPT_TO_PRINTER;
        end else begin
          next_state = INTERRUPT_CPU_WRITE;
        end
      end
      INTERRUPT_TO_PRINTER: begin
        if (i_rdy == 'b1 && ready == 'b0) begin
          next_state = IDLE;
        end else begin
          next_state = INTERRUPT_TO_PRINTER;
        end
      end
      default: begin
        next_state = IDLE;
      end
    endcase
  end


  // status and buffer
  always @(*) begin
    case (state)
      IDLE: begin
        status         = {7'b1000000, mode};  // reset to POC ready
        printer_data   = 8'b0;  // every cycle reset the printer data
        enable_printer = 1'b0;  // every cycle reset the printer status
      end
      POLLING_CPU_WRITE: begin
        // CPU needs to write both buffer and status in this state
        if (i_rw == 1'b1 && i_addr == 1'b1) begin
          buffer = i_din;
        end
        if (i_rw == 1'b1 && i_addr == 1'b0) begin
          status = i_din;
        end
      end
      INTERRUPT_CPU_WRITE: begin
        if (i_rw == 1'b1 && i_addr == 1'b1) begin
          buffer = i_din;
        end
        if (i_rw == 1'b1 && i_addr == 1'b0) begin
          status = i_din;
        end
      end
    endcase
  end

  always @(posedge i_clk or negedge i_rst_n) begin
    if (!i_rst_n) begin
      enable_printer <= 1'b0;
      tr_triggered   <= 1'b0;
    end else begin
      if (state == POLLING_TO_PRINTER || state == INTERRUPT_TO_PRINTER) begin
        if (ready == 1'b1 && enable_printer == 1'b0 && tr_triggered == 1'b0) begin
          printer_data   <= buffer;
          enable_printer <= 1'b1;
        end else if (enable_printer == 1'b1) begin
          enable_printer <= 1'b0;
          tr_triggered   <= 1'b1;
        end
      end else begin
        tr_triggered <= 1'b0;
      end
    end
  end

  // Assignments
  assign o_irq = ~interrupt;
  assign o_tr = enable_printer;
  assign o_pd = printer_data;
  assign o_dout = status;

  assign interrupt = status[7] & status[0];

endmodule

processor.v
// Date: 2025.3.20
// Author: LiPtP
// Description: Simple 8-bit processor generating status and data for POC

module PROCESSOR (
    i_clk,
    i_rst_n,
    i_irq,
    i_dout,
    i_data,
    o_din,
    o_addr,
    o_rw
);


  input wire i_clk;
  input wire i_rst_n;
  input wire i_irq;
  input wire [7:0] i_dout;  // Data from POC (specifically status info)
  input wire [7:0] i_data;  // Data from top module

  output reg [7:0] o_din;  // Data to POC
  output wire o_addr;
  output wire o_rw;
  
  // Internal registers
  reg [7:0] poc_status;
  reg address;
  reg rw;

  // State registers
  reg [2:0] state, next_state;

  // Status tracking signals
  reg set_data_done;
  reg read_status_done;

  // Mode signal from poc_status[0]
  wire mode = poc_status[0];
  wire interrupt = i_irq;

  // State encoding
  parameter STATUS = 1'b0;
  parameter BUFFER = 1'b1;

  parameter IDLE = 3'b000;
  parameter READ_FROM_POC = 3'b001;
  parameter SET_DATA = 3'b010;
  parameter WRITE_DATA = 3'b011;
  parameter DELAY = 3'b100;
  parameter WRITE_STATUS = 3'b101;

  // State transition
  always @(posedge i_clk or negedge i_rst_n) begin
    if (!i_rst_n) state <= IDLE;
    else state <= next_state;
  end

  // Next state logic
  always @(*) begin
    case (state)
      IDLE: begin
        if (mode == 1'b0) next_state = READ_FROM_POC;
        else if (interrupt == 1'b0) next_state = SET_DATA;
        else next_state = IDLE;
      end
      READ_FROM_POC: begin
        if (read_status_done) next_state = SET_DATA;
        else next_state = READ_FROM_POC;
      end
      SET_DATA: begin
        if (set_data_done) next_state = WRITE_DATA;
        else next_state = SET_DATA;
      end
      WRITE_DATA: begin
        next_state = DELAY;  // wait one clock cycle for poc read delay
      end
      DELAY: begin
        next_state = WRITE_STATUS;
      end
      WRITE_STATUS: begin
        next_state = IDLE;
      end
      default: next_state = IDLE;
    endcase
  end

  // Control logic for address and rw
  always @(*) begin
    case (state)
      IDLE: begin
        address = STATUS;
        rw = 1'b0;
      end
      READ_FROM_POC: begin
        rw = 1'b0;
        address = STATUS;
      end
      SET_DATA: begin
        rw = 1'b0;
        address = BUFFER;
      end
      WRITE_DATA: begin
        rw = 1'b1;
        address = BUFFER;
      end
      WRITE_STATUS: begin
        rw = 1'b1;
        address = STATUS;
      end
    endcase
  end

  // Output data control
  always @(*) begin
    set_data_done = 1'b0;
    if (state == WRITE_DATA || state == IDLE) begin
      set_data_done = 1'b0;
    end else begin
      if (address == STATUS) o_din = poc_status;
      else begin
        o_din = i_data;
        set_data_done = 1'b1;
      end
    end
  end

  // poc_status and read_status_done update
  always @(posedge i_clk or negedge i_rst_n) begin
    if (!i_rst_n) begin
      read_status_done <= 1'b0;
      poc_status <= 8'b0;
    end else begin
      case (state)
        IDLE: begin
          read_status_done <= 1'b0;
        end
        READ_FROM_POC: begin
          poc_status <= i_dout;
          read_status_done <= 1'b1;
        end
        SET_DATA: begin
          poc_status[7] <= 1'b0;
        end
      endcase
    end
  end

  // Assign output signals
  assign o_rw   = rw;
  assign o_addr = address;

endmodule

top.v
// Date: 2025.2.27
// Author: LiPtP
// Description: Top layer of POC, describing interconnections of three lower modules

module TOP (
    i_clk,
    i_rst_n,
    i_data,
    i_mode,
    o_tr,
    o_pd,
    o_rdy,
    o_data,
    o_rw,
    o_addr,
    o_irq,
    o_data_poc_to_processor,
    o_data_processor_to_poc
);
// I/O

input wire i_clk;
input wire i_rst_n;
input wire i_mode;
input wire [7:0] i_data;

output wire [7:0] o_data;
output wire o_irq;
output wire o_addr;
output wire o_rw;
output wire o_tr;
output wire [7:0] o_pd;
output wire o_rdy;
output wire [7:0] o_data_poc_to_processor;
output wire [7:0] o_data_processor_to_poc;
// CPU/POC connections

wire irq;
wire addr;
wire [7:0] data_processor_to_POC;
wire [7:0] data_POC_to_processor;
wire rw;

// POC/Printer connections

wire tr;
wire [7:0] pd;
wire rdy;

// Instantiations

PROCESSOR u_processor (
    .i_clk(i_clk),               // 时钟输入
    .i_rst_n(i_rst_n),           // 复位信号，低有效
    .i_irq(irq),                            // 中断
    .i_data(i_data),                        // Directly from TB
    .i_dout(data_POC_to_processor),         // 从 POC 读取的数据
    .o_din(data_processor_to_POC),          // 发送到 POC 的数据
    .o_addr(addr),                          // 地址信号
    .o_rw(rw)                  // 读/写信号
);

POC u_poc (
    .i_addr(addr),
    .o_dout(data_POC_to_processor),
    .i_din(data_processor_to_POC),
    .i_rw(rw),
    .i_clk(i_clk),
    .i_rst_n(i_rst_n),
    .i_mode(i_mode),
    .o_irq(irq),
    .i_rdy(rdy),
    .o_tr(tr),
    .o_pd(pd)
);

PRINTER u_printer (
    .i_tr(tr),
    .i_pd(pd),
    .o_rdy(rdy),
    .i_clk(i_clk),
    .i_rst_n(i_rst_n),
    .o_data(o_data)         // directly output to tb
);

// assignments

// CPU/POC 
assign o_irq = irq;
assign o_addr = addr;
assign o_rw = rw;
assign o_data_processor_to_poc = data_processor_to_POC;
assign o_data_poc_to_processor = data_POC_to_processor;

// POC/Printer 
assign o_tr = tr;
assign o_pd = pd;
assign o_rdy = rdy;


endmodule

tb.v
// Date: 2025.3.10
// Author: LiPtP
// Description: Testbench for TOP module
`timescale 1ns / 1ps
module tb_POC;

  // Clock and reset
  reg clk;
  reg reset;

  // Input to modules
  reg [7:0] data_in;
  reg mode;

  // Output from modules
  wire [7:0] printer_data;
  wire printer_tr;
  wire [7:0] poc_pd;
  wire poc_ready;

  wire rw;
  wire addr;
  wire [7:0] data_POC_to_processor;
  wire [7:0] data_processor_to_POC;
  wire irq_n;

  // Clock generation (50MHz, 20ns period)
  always #10 clk = ~clk;

  // Reset sequence
  initial begin
    clk = 0;
    reset = 0;
    mode = 0;
    data_in = 8'b0;

    #50 reset = 1;  // 50ns delay to allow reset propagation
  end

  // Mode switching after 100,000 ns
  initial begin
    #100000 mode = 1;
  end

  // Periodic Data Input
  initial begin
    #100;
    while (1) begin
      if (mode == 0) begin
        data_in = 8'b00000000;
        #340;
        data_in = 8'b00000001;
        #340;
        data_in = 8'b00000010;
        #340;
        data_in = 8'b00000011;
        #340;
        data_in = 8'b00000100;
        #340;
        data_in = 8'b00000101;
        #340;
        data_in = 8'b00000110;
        #340;
        data_in = 8'b00000111;
        #340;
        data_in = 8'b00001000;
        #340;
        data_in = 8'b00001001;
        #340;
        data_in = 8'b00001010;
        #340;
        data_in = 8'b00001011;
        #340;
        data_in = 8'b00001100;
        #340;
        data_in = 8'b00001101;
        #340;
        data_in = 8'b00001110;
        #340;
        data_in = 8'b00001111;
        #340;
        data_in = 8'b00010000;
        #340;
        data_in = 8'b00010001;
        #340;
        data_in = 8'b00010010;
        #340;
        data_in = 8'b00010011;
        #340;
        data_in = 8'b00010100;
        #340;
      end else begin
        data_in = 8'b00000000;
        #320;
        data_in = 8'b00000001;
        #320;
        data_in = 8'b00000010;
        #320;
        data_in = 8'b00000011;
        #320;
        data_in = 8'b00000100;
        #320;
        data_in = 8'b00000101;
        #320;
        data_in = 8'b00000110;
        #320;
        data_in = 8'b00000111;
        #320;
        data_in = 8'b00001000;
        #320;
        data_in = 8'b00001001;
        #320;
        data_in = 8'b00001010;
        #320;
        data_in = 8'b00001011;
        #320;
        data_in = 8'b00001100;
        #320;
        data_in = 8'b00001101;
        #320;
        data_in = 8'b00001110;
        #320;
        data_in = 8'b00001111;
        #320;
        data_in = 8'b00010000;
        #320;
        data_in = 8'b00010001;
        #320;
        data_in = 8'b00010010;
        #320;
        data_in = 8'b00010011;
        #320;
        data_in = 8'b00010100;
        #320;

      end
    end
  end

  // Dump waveforms
  initial begin
    $dumpfile("poc.vcd");
    $dumpvars(0, tb_POC);
    #200000 $finish;
  end

  // Instantiate DUT
  TOP u_dut (
      .i_clk(clk),
      .i_rst_n(reset),
      .i_data(data_in),
      .i_mode(mode),
      .o_tr(printer_tr),
      .o_pd(poc_pd),
      .o_rdy(poc_ready),
      .o_data(printer_data),
      .o_rw(rw),
      .o_addr(addr),
      .o_irq(irq_n),
      .o_data_poc_to_processor(data_POC_to_processor),
      .o_data_processor_to_poc(data_processor_to_POC)
  );

endmodule

poc.vcd
$date
	Thu Mar 20 19:36:12 2025
$end
$version
	Icarus Verilog
$end
$timescale
	1ps
$end
$scope module tb_POC $end
$var wire 1 ! rw $end
$var wire 1 " printer_tr $end
$var wire 8 # printer_data [7:0] $end
$var wire 1 $ poc_ready $end
$var wire 8 % poc_pd [7:0] $end
$var wire 1 & irq_n $end
$var wire 8 ' data_processor_to_POC [7:0] $end
$var wire 8 ( data_POC_to_processor [7:0] $end
$var wire 1 ) addr $end
$var reg 1 * clk $end
$var reg 8 + data_in [7:0] $end
$var reg 1 , mode $end
$var reg 1 - reset $end
$scope module u_dut $end
$var wire 1 * i_clk $end
$var wire 8 . i_data [7:0] $end
$var wire 1 , i_mode $end
$var wire 1 - i_rst_n $end
$var wire 1 ) o_addr $end
$var wire 8 / o_data_poc_to_processor [7:0] $end
$var wire 8 0 o_data_processor_to_poc [7:0] $end
$var wire 1 & o_irq $end
$var wire 8 1 o_pd [7:0] $end
$var wire 1 $ o_rdy $end
$var wire 1 ! o_rw $end
$var wire 1 " o_tr $end
$var wire 1 2 tr $end
$var wire 1 3 rw $end
$var wire 1 4 rdy $end
$var wire 8 5 pd [7:0] $end
$var wire 8 6 o_data [7:0] $end
$var wire 1 7 irq $end
$var wire 8 8 data_processor_to_POC [7:0] $end
$var wire 8 9 data_POC_to_processor [7:0] $end
$var wire 1 : addr $end
$scope module u_poc $end
$var wire 1 * i_clk $end
$var wire 1 , i_mode $end
$var wire 1 - i_rst_n $end
$var wire 1 ; interrupt $end
$var wire 8 < o_dout [7:0] $end
$var wire 1 7 o_irq $end
$var wire 1 2 o_tr $end
$var wire 8 = o_pd [7:0] $end
$var wire 1 3 i_rw $end
$var wire 1 4 i_rdy $end
$var wire 8 > i_din [7:0] $end
$var wire 1 : i_addr $end
$var parameter 3 ? IDLE $end
$var parameter 3 @ INTERRUPT_CPU_WRITE $end
$var parameter 3 A INTERRUPT_TO_PRINTER $end
$var parameter 3 B POLLING_CPU_WRITE $end
$var parameter 3 C POLLING_TO_PRINTER $end
$var reg 8 D buffer [7:0] $end
$var reg 1 2 enable_printer $end
$var reg 1 E mode $end
$var reg 3 F next_state [2:0] $end
$var reg 8 G printer_data [7:0] $end
$var reg 1 H ready $end
$var reg 3 I state [2:0] $end
$var reg 8 J status [7:0] $end
$var reg 1 K tr_triggered $end
$upscope $end
$scope module u_printer $end
$var wire 1 * i_clk $end
$var wire 8 L i_pd [7:0] $end
$var wire 1 - i_rst_n $end
$var wire 1 2 i_tr $end
$var wire 8 M o_data [7:0] $end
$var wire 1 4 o_rdy $end
$var parameter 1 N BUSY $end
$var parameter 1 O IDLE $end
$var reg 3 P count [2:0] $end
$var reg 1 Q next_state $end
$var reg 1 R state $end
$upscope $end
$scope module u_processor $end
$var wire 1 * i_clk $end
$var wire 8 S i_data [7:0] $end
$var wire 8 T i_dout [7:0] $end
$var wire 1 7 i_irq $end
$var wire 1 - i_rst_n $end
$var wire 1 U interrupt $end
$var wire 1 : o_addr $end
$var wire 1 3 o_rw $end
$var wire 1 V mode $end
$var parameter 1 W BUFFER $end
$var parameter 3 X DELAY $end
$var parameter 3 Y IDLE $end
$var parameter 3 Z READ_FROM_POC $end
$var parameter 3 [ SET_DATA $end
$var parameter 1 \ STATUS $end
$var parameter 3 ] WRITE_DATA $end
$var parameter 3 ^ WRITE_STATUS $end
$var reg 1 : address $end
$var reg 3 _ next_state [2:0] $end
$var reg 8 ` o_din [7:0] $end
$var reg 8 a poc_status [7:0] $end
$var reg 1 b read_status_done $end
$var reg 1 3 rw $end
$var reg 1 c set_data_done $end
$var reg 3 d state [2:0] $end
$upscope $end
$upscope $end
$upscope $end
$enddefinitions $end
$comment Show the parameter values. $end
$dumpall
b101 ^
b11 ]
0\
b10 [
b1 Z
b0 Y
b100 X
1W
0O
1N
b10 C
b1 B
b100 A
b11 @
b0 ?
$end
#0
$dumpvars
b0 d
0c
0b
b0 a
b0 `
b1 _
0V
1U
b10000000 T
b0 S
0R
0Q
b0 P
bx M
b0 L
0K
b10000000 J
b0 I
0H
b0 G
b0 F
0E
bx D
b0 >
b0 =
b10000000 <
0;
0:
b10000000 9
b0 8
17
bx 6
b0 5
14
03
02
b0 1
b0 0
b10000000 /
b0 .
0-
0,
b0 +
0*
0)
b10000000 (
b0 '
1&
b0 %
1$
bx #
0"
0!
$end
#10000
1*
#20000
0*
#30000
1*
#40000
0*
#50000
1H
b1 d
1*
1-
#60000
0*
#70000
b10000000 '
b10000000 0
b10000000 8
b10000000 >
b10000000 `
b10 _
1b
b10000000 a
1*
#80000
0*
#90000
b11 _
1c
b0 '
b0 0
b0 8
b0 >
b0 `
1)
1:
b10 d
1*
#100000
0*
#110000
b1 F
1!
13
0c
b100 _
b11 d
b0 a
1*
#120000
0*
#130000
b0 D
1c
b101 _
b1 I
b100 d
1*
#140000
0*
#150000
b10 F
b0 (
b0 /
b0 9
b0 <
b0 T
b0 J
0c
0)
0:
b0 _
b101 d
1*
#160000
0*
#170000
0!
03
b1 _
b10 I
b0 d
1*
#180000
0*
#190000
1Q
b1 d
0b
1"
12
1*
#200000
0*
#210000
0$
04
1R
1K
0"
02
1b
1*
#220000
0*
#230000
0H
b1 P
1*
#240000
0*
#250000
b10 P
1*
#260000
0*
#270000
b11 P
1*
#280000
0*
#290000
b100 P
b0 #
b0 6
b0 M
1*
#300000
0*
#310000
b101 P
1*
#320000
0*
#330000
b110 P
1*
#340000
0*
#350000
0Q
b111 P
1*
#360000
0*
#370000
b0 F
1$
14
b0 P
0R
1*
#380000
0*
#390000
b10000000 (
b10000000 /
b10000000 9
b10000000 <
b10000000 T
b10000000 J
1H
b0 I
1*
#400000
0*
#410000
b10000000 '
b10000000 0
b10000000 8
b10000000 >
b10000000 `
b10 _
0K
b10000000 a
1*
#420000
0*
#430000
b11 _
1c
b0 '
b0 0
b0 8
b0 >
b0 `
1)
1:
b10 d
1*
#440000
b1 '
b1 0
b1 8
b1 >
b1 `
1c
0*
b1 +
b1 .
b1 S
#450000
b1 F
0c
1!
13
b100 _
b0 a
b11 d
1*
#460000
0*
#470000
1c
b101 _
b1 D
b100 d
b1 I
1*
#480000
0*
#490000
b10 F
b0 (
b0 /
b0 9
b0 <
b0 T
b0 J
b0 '
b0 0
b0 8
b0 >
b0 `
0c
0)
0:
b0 _
b101 d
1*
#500000
0*
#510000
0!
03
b1 _
b0 d
b10 I
1*
#520000
0*
#530000
1Q
1"
12
b1 %
b1 1
b1 5
b1 =
b1 G
b1 L
0b
b1 d
1*
#540000
0*
#550000
0$
04
1b
1K
0"
02
1R
1*
#560000
0*
#570000
b1 P
0H
1*
#580000
0*
#590000
b10 P
1*
#600000
0*
#610000
b11 P
1*
#620000
0*
#630000
b100 P
b1 #
b1 6
b1 M
1*
#640000
0*
#650000
b101 P
1*
#660000
0*
#670000
b110 P
1*
#680000
0*
#690000
0Q
b111 P
1*
#700000
0*
#710000
b0 F
1$
14
0R
b0 P
1*
#720000
0*
#730000
b0 %
b0 1
b0 5
b0 =
b0 G
b0 L
b10000000 (
b10000000 /
b10000000 9
b10000000 <
b10000000 T
b10000000 J
1H
b0 I
1*
#740000
0*
#750000
b10000000 '
b10000000 0
b10000000 8
b10000000 >
b10000000 `
b10 _
b10000000 a
0K
1*
#760000
0*
#770000
b11 _
1c
b1 '
b1 0
b1 8
b1 >
b1 `
1)
1:
b10 d
1*
#780000
b10 '
b10 0
b10 8
b10 >
b10 `
1c
0*
b10 +
b10 .
b10 S
#790000
b1 F
1!
13
0c
b100 _
b11 d
b0 a
1*
#800000
0*
#810000
b10 D
1c
b101 _
b1 I
b100 d
1*
#820000
0*
#830000
b10 F
b0 (
b0 /
b0 9
b0 <
b0 T
b0 J
b0 '
b0 0
b0 8
b0 >
b0 `
0c
0)
0:
b0 _
b101 d
1*
#840000
0*
#850000
0!
03
b1 _
b10 I
b0 d
1*
#860000
0*
#870000
1Q
b1 d
0b
1"
12
b10 %
b10 1
b10 5
b10 =
b10 G
b10 L
1*
#880000
0*
#890000
0$
04
1R
1K
0"
02
1b
1*
#900000
0*
#910000
0H
b1 P
1*
#920000
0*
#930000
b10 P
1*
#940000
0*
#950000
b11 P
1*
#960000
0*
#970000
b100 P
b10 #
b10 6
b10 M
1*
#980000
0*
#990000
b101 P
1*
#1000000
0*
#1010000
b110 P
1*
#1020000
0*
#1030000
0Q
b111 P
1*
#1040000
0*
#1050000
b0 F
1$
14
b0 P
0R
1*
#1060000
0*
#1070000
b0 %
b0 1
b0 5
b0 =
b0 G
b0 L
b10000000 (
b10000000 /
b10000000 9
b10000000 <
b10000000 T
b10000000 J
1H
b0 I
1*
#1080000
0*
#1090000
b10000000 '
b10000000 0
b10000000 8
b10000000 >
b10000000 `
b10 _
0K
b10000000 a
1*
#1100000
0*
#1110000
b11 _
1c
b10 '
b10 0
b10 8
b10 >
b10 `
1)
1:
b10 d
1*
#1120000
b11 '
b11 0
b11 8
b11 >
b11 `
1c
0*
b11 +
b11 .
b11 S
#1130000
b1 F
0c
1!
13
b100 _
b0 a
b11 d
1*
#1140000
0*
#1150000
1c
b101 _
b11 D
b100 d
b1 I
1*
#1160000
0*
#1170000
b10 F
b0 (
b0 /
b0 9
b0 <
b0 T
b0 J
b0 '
b0 0
b0 8
b0 >
b0 `
0c
0)
0:
b0 _
b101 d
1*
#1180000
0*
#1190000
0!
03
b1 _
b0 d
b10 I
1*
#1200000
0*
#1210000
1Q
1"
12
b11 %
b11 1
b11 5
b11 =
b11 G
b11 L
0b
b1 d
1*
#1220000
0*
#1230000
0$
04
1b
1K
0"
02
1R
1*
#1240000
0*
#1250000
b1 P
0H
1*
#1260000
0*
#1270000
b10 P
1*
#1280000
0*
#1290000
b11 P
1*
#1300000
0*
#1310000
b100 P
b11 #
b11 6
b11 M
1*
#1320000
0*
#1330000
b101 P
1*
#1340000
0*
#1350000
b110 P
1*
#1360000
0*
#1370000
0Q
b111 P
1*
#1380000
0*
#1390000
b0 F
1$
14
0R
b0 P
1*
#1400000
0*
#1410000
b0 %
b0 1
b0 5
b0 =
b0 G
b0 L
b10000000 (
b10000000 /
b10000000 9
b10000000 <
b10000000 T
b10000000 J
1H
b0 I
1*
#1420000
0*
#1430000
b10000000 '
b10000000 0
b10000000 8
b10000000 >
b10000000 `
b10 _
b10000000 a
0K
1*
#1440000
0*
#1450000
b11 _
1c
b11 '
b11 0
b11 8
b11 >
b11 `
1)
1:
b10 d
1*
#1460000
b100 '
b100 0
b100 8
b100 >
b100 `
1c
0*
b100 +
b100 .
b100 S
#1470000
b1 F
1!
13
0c
b100 _
b11 d
b0 a
1*
#1480000
0*
#1490000
b100 D
1c
b101 _
b1 I
b100 d
1*
#1500000
0*
#1510000
b10 F
b0 (
b0 /
b0 9
b0 <
b0 T
b0 J
b0 '
b0 0
b0 8
b0 >
b0 `
0c
0)
0:
b0 _
b101 d
1*
#1520000
0*
#1530000
0!
03
b1 _
b10 I
b0 d
1*
#1540000
0*
#1550000
1Q
b1 d
0b
1"
12
b100 %
b100 1
b100 5
b100 =
b100 G
b100 L
1*
#1560000
0*
#1570000
0$
04
1R
1K
0"
02
1b
1*
#1580000
0*
#1590000
0H
b1 P
1*
#1600000
0*
#1610000
b10 P
1*
#1620000
0*
#1630000
b11 P
1*
#1640000
0*
#1650000
b100 P
b100 #
b100 6
b100 M
1*
#1660000
0*
#1670000
b101 P
1*
#1680000
0*
#1690000
b110 P
1*
#1700000
0*
#1710000
0Q
b111 P
1*
#1720000
0*
#1730000
b0 F
1$
14
b0 P
0R
1*
#1740000
0*
#1750000
b0 %
b0 1
b0 5
b0 =
b0 G
b0 L
b10000000 (
b10000000 /
b10000000 9
b10000000 <
b10000000 T
b10000000 J
1H
b0 I
1*
#1760000
0*
#1770000
b10000000 '
b10000000 0
b10000000 8
b10000000 >
b10000000 `
b10 _
0K
b10000000 a
1*
#1780000
0*
#1790000
b11 _
1c
b100 '
b100 0
b100 8
b100 >
b100 `
1)
1:
b10 d
1*
#1800000
b101 '
b101 0
b101 8
b101 >
b101 `
1c
0*
b101 +
b101 .
b101 S
#1810000
b1 F
0c
1!
13
b100 _
b0 a
b11 d
1*
#1820000
0*
#1830000
1c
b101 _
b101 D
b100 d
b1 I
1*
#1840000
0*
#1850000
b10 F
b0 (
b0 /
b0 9
b0 <
b0 T
b0 J
b0 '
b0 0
b0 8
b0 >
b0 `
0c
0)
0:
b0 _
b101 d
1*
#1860000
0*
#1870000
0!
03
b1 _
b0 d
b10 I
1*
#1880000
0*
#1890000
1Q
1"
12
b101 %
b101 1
b101 5
b101 =
b101 G
b101 L
0b
b1 d
1*
#1900000
0*
#1910000
0$
04
1b
1K
0"
02
1R
1*
#1920000
0*
#1930000
b1 P
0H
1*
#1940000
0*
#1950000
b10 P
1*
#1960000
0*
#1970000
b11 P
1*
#1980000
0*
#1990000
b100 P
b101 #
b101 6
b101 M
1*
#2000000
0*
#2010000
b101 P
1*
#2020000
0*
#2030000
b110 P
1*
#2040000
0*
#2050000
0Q
b111 P
1*
#2060000
0*
#2070000
b0 F
1$
14
0R
b0 P
1*
#2080000
0*
#2090000
b0 %
b0 1
b0 5
b0 =
b0 G
b0 L
b10000000 (
b10000000 /
b10000000 9
b10000000 <
b10000000 T
b10000000 J
1H
b0 I
1*
#2100000
0*
#2110000
b10000000 '
b10000000 0
b10000000 8
b10000000 >
b10000000 `
b10 _
b10000000 a
0K
1*
#2120000
0*
#2130000
b11 _
1c
b101 '
b101 0
b101 8
b101 >
b101 `
1)
1:
b10 d
1*
#2140000
b110 '
b110 0
b110 8
b110 >
b110 `
1c
0*
b110 +
b110 .
b110 S
#2150000
b1 F
1!
13
0c
b100 _
b11 d
b0 a
1*
#2160000
0*
#2170000
b110 D
1c
b101 _
b1 I
b100 d
1*
#2180000
0*
#2190000
b10 F
b0 (
b0 /
b0 9
b0 <
b0 T
b0 J
b0 '
b0 0
b0 8
b0 >
b0 `
0c
0)
0:
b0 _
b101 d
1*
#2200000
0*
#2210000
0!
03
b1 _
b10 I
b0 d
1*
#2220000
0*
#2230000
1Q
b1 d
0b
1"
12
b110 %
b110 1
b110 5
b110 =
b110 G
b110 L
1*
#2240000
0*
#2250000
0$
04
1R
1K
0"
02
1b
1*
#2260000
0*
#2270000
0H
b1 P
1*
#2280000
0*
#2290000
b10 P
1*
#2300000
0*
#2310000
b11 P
1*
#2320000
0*
#2330000
b100 P
b110 #
b110 6
b110 M
1*
#2340000
0*
#2350000
b101 P
1*
#2360000
0*
#2370000
b110 P
1*
#2380000
0*
#2390000
0Q
b111 P
1*
#2400000
0*
#2410000
b0 F
1$
14
b0 P
0R
1*
#2420000
0*
#2430000
b0 %
b0 1
b0 5
b0 =
b0 G
b0 L
b10000000 (
b10000000 /
b10000000 9
b10000000 <
b10000000 T
b10000000 J
1H
b0 I
1*
#2440000
0*
#2450000
b10000000 '
b10000000 0
b10000000 8
b10000000 >
b10000000 `
b10 _
0K
b10000000 a
1*
#2460000
0*
#2470000
b11 _
1c
b110 '
b110 0
b110 8
b110 >
b110 `
1)
1:
b10 d
1*
#2480000
b111 '
b111 0
b111 8
b111 >
b111 `
1c
0*
b111 +
b111 .
b111 S
#2490000
b1 F
0c
1!
13
b100 _
b0 a
b11 d
1*
#2500000
0*
#2510000
1c
b101 _
b111 D
b100 d
b1 I
1*
#2520000
0*
#2530000
b10 F
b0 (
b0 /
b0 9
b0 <
b0 T
b0 J
b0 '
b0 0
b0 8
b0 >
b0 `
0c
0)
0:
b0 _
b101 d
1*
#2540000
0*
#2550000
0!
03
b1 _
b0 d
b10 I
1*
#2560000
0*
